mendi/__init__.py
mendi/mendi.py
mendi-0.1.0.dist-info/LICENSE
mendi-0.1.0.dist-info/WHEEL
mendi-0.1.0.dist-info/METADATA
mendi-0.1.0.dist-info/RECORD
