Metadata-Version: 2.1
Name: mendi
Version: 0.1.0
Summary: A python library for building menu-driven CLI applications.
Home-page: https://github.com/aahnik/mendi
License: MIT
Keywords: python,cli,framework,library,menu
Author: aahnik
Author-email: daw@aahnik.dev
Requires-Python: >=3.8,<4.0
Classifier: Development Status :: 4 - Beta
Classifier: Intended Audience :: Education
Classifier: Intended Audience :: Information Technology
Classifier: License :: OSI Approved :: MIT License
Classifier: Natural Language :: English
Classifier: Operating System :: OS Independent
Classifier: Programming Language :: Python
Classifier: Programming Language :: Python :: 3
Classifier: Programming Language :: Python :: 3.8
Classifier: Programming Language :: Python :: 3.9
Requires-Dist: tabulate (>=0.8.9,<0.9.0)
Project-URL: Repository, https://github.com/aahnik/mendi
